{
    "general": {
        "lstr": "通用搜索"
    },
    "common": {
        "dname": "常用",
        "btns": {
            "all":{
                "label":"all",
                "use_other_engine":[
                    "baidu",
                    "sogou",
                    "360"
                ]
            },
            "sogou": {
                "label": "搜狗",
                "use_other_engine": "sogou"
            },
            "360so": {
                "label": "360so",
                "use_other_engine": "360so"
            },
            "baidu": {
                "label": "百度",
                "use_other_engine": "baidu"
            },
            "bing":{
                "label": "Bing",
                "use_other_engine":"bing"
            }
        }
    },
    "f_google": {
        "fav": "google"
    },
    "many_chinese": {
        "dname": "齐搜",
        "btns": {
            "all": {
                "label": "all",
                "use_other_engine": [
                    "chinaso",
                    "yandex"
                ]
            },
            "chinaso": {
                "label": "国搜",
                "use_other_engine": "chinaso"
            },
            "yandex": {
                "label": "Yandex",
                "use_other_engine": "yandex"
            }
        }
    },
    "video": {
        "lstr": "影音视听"
    },
    "imdb": {
        "dname": "IMDb",
        "addr": "https://www.imdb.com",
        "action": "https://www.imdb.com/find/",
        "kw_key": "q",
        "unknow_full_url": "https://www.imdb.com/find/?q={0}&ref_=nv_sr_sm"
    },
    "greatposterwall": {
        "dname": "GreatPosterWall",
        "full_url": "https://greatposterwall.com/torrents.php?searchstr={0}"
    },
    "knownledge": {
        "lstr": "知识问答"
    },
    "acadamic": {
        "dname": "学术文献",
        "btns": {
            "pubmed": {
                "label": "PubMed",
                "use_other_engine": "pubmed"
            },
            "google": {
                "label": "Google",
                "use_other_engine": "google_scholar"
            },
            "bing": {
                "label": "Bing",
                "use_other_engine": "bing_ac"
            },
            "baidu": {
                "label": "Baidu",
                "use_other_engine": {
                    "engine": "baidu_xuesu",
                    "btn": "journal"
                }
            }
        }
    },
    "f_zhihu": {
        "fav": "zhihu"
    },
    "programming": {
        "dname": "编程资料",
        "btns": {
            "github": {
                "label": "Github",
                "use_other_engine": "github"
            },
            "pypi": {
                "label": "PyPI",
                "action": "https://pypi.org/search/",
                "kw_key": "q"
            },
            "doc": {
                "label": "std doc",
                "action": "https://doc.rust-lang.org/std/index.html",
                "kw_key": "search"
            },
            "crates": {
                "label": "crates.io",
                "action": "https://crates.io/search",
                "kw_key": "q"
            }
        }
    }
}